status_codes/__init__.py
status_codes/main.py
status_codes-1.3.0.dist-info/METADATA
status_codes-1.3.0.dist-info/WHEEL
status_codes-1.3.0.dist-info/top_level.txt
status_codes-1.3.0.dist-info/RECORD
