Metadata-Version: 2.1
Name: status_codes
Version: 1.3.0
Summary: HTTP status code responses with predefined or custom messages for easy integration into web applications and APIs.
